{
  "dependencies": [],
  "tasks": {
    "Water": {
      "type": "heracles:item",
      "item": "minecraft:water_bucket",
      "amount": 1,
      "collection": "AUTOMATIC",
      "icon": {
        "item": {
          "id": "minecraft:water_bucket",
          "count": 1
        },
        "type": "heracles:item"
      }
    },
    "pickaxe": {
      "title": "Pick Me",
      "icon": {
        "item": {
          "id": "minecraft:stone_pickaxe",
          "count": 1,
          "nbt": {
            "Damage": 0
          }
        },
        "type": "heracles:item"
      },
      "recipes": [
        "minecraft:stone_pickaxe"
      ],
      "type": "heracles:recipe"
    },
    "minecraft:stone_sword": {
      "title": "Sword Me",
      "icon": {
        "item": {
          "id": "minecraft:stone_sword",
          "count": 1,
          "nbt": {
            "Damage": 0
          }
        },
        "type": "heracles:item"
      },
      "recipes": [
        "minecraft:stone_sword"
      ],
      "type": "heracles:recipe"
    },
    "my recipe": {
      "title": "Create a Campfire",
      "icon": {
        "item": {
          "id": "minecraft:campfire",
          "count": 1
        },
        "type": "heracles:item"
      },
      "recipes": [
        "minecraft:campfire"
      ],
      "type": "heracles:recipe"
    },
    "axe": {
      "title": "Axe me",
      "icon": {
        "item": {
          "id": "minecraft:stone_axe",
          "count": 1,
          "nbt": {
            "Damage": 0
          }
        },
        "type": "heracles:item"
      },
      "recipes": [
        "minecraft:stone_axe"
      ],
      "type": "heracles:recipe"
    },
    "Shovel Me": {
      "title": "Shovel Me",
      "icon": {
        "item": {
          "id": "minecraft:stone_shovel",
          "count": 1,
          "nbt": {
            "Damage": 0
          }
        },
        "type": "heracles:item"
      },
      "recipes": [
        "minecraft:stone_shovel"
      ],
      "type": "heracles:recipe"
    },
    "stone": {
      "type": "heracles:item",
      "item": "minecraft:stone",
      "amount": 30,
      "collection": "AUTOMATIC",
      "title": "30 Stone Shelter",
      "icon": {
        "item": {
          "id": "minecraft:stone",
          "count": 1
        },
        "type": "heracles:item"
      }
    }
  },
  "rewards": {
    "test age": {
      "title": "Who's on First",
      "icon": {
        "item": {
          "id": "minecraft:stone_sword",
          "count": 1,
          "nbt": {
            "Damage": 0
          }
        },
        "type": "heracles:item"
      },
      "command": "/thitemstages add @s whos_on_first",
      "type": "heracles:command"
    }
  },
  "display": {
    "subtitle": {
      "text": ""
    },
    "description": [
      "__**Immediate Survival**__",
      "**Mission Protocol: Phase 2 - Immediate Survival**",
      "",
      "**Mission Overview:**",
      "After securing the emergency supplies, your next critical task is to ensure the immediate survival of the crew on this unfamiliar, floating island. The ship has crash-landed in a large crater at the center of the island. Follow these steps to establish a safe and secure base for further exploration and survival.",
      "",
      "**Task Details:**",
      "",
      "    **Assess the Crash Site:**",
      "        Carefully inspect the crash site for any additional supplies or salvageable materials.",
      "        Be cautious of unstable debris and potential hazards.",
      "",
      "    **Establish a Perimeter:**",
      "        Clear the area around the crash site to create a secure perimeter.",
      "        Use available materials to mark the boundary and set up simple defenses against potential threats.",
      "",
      "    **Construct a Shelter:**",
      "        Use salvaged ship materials and local resources to construct a temporary shelter.",
      "        Ensure the shelter provides protection from the elements and any hostile creatures.",
      "",
      "    **Secure a Water Source:**",
      "        Identify and secure a clean water source nearby.",
      "        If no immediate source is available, set up a rainwater collection system or use purification methods on                   available water.",
      "",
      "    **Gather Initial Food Supplies:**",
      "        Forage for edible plants, fruits, and other natural resources on the island.",
      "        Set up traps or fishing lines if there is any water body.",
      "",
      "    **Establish a Fire:**",
      "        Gather wood and other combustible materials to start a fire.",
      "        Use the fire for warmth, cooking, and signaling if necessary.",
      "",
      "    **Set Up Basic Tools and Equipment:**",
      "        Craft essential tools using available resources (e.g., pickaxe, axe, shovel).",
      "        Use these tools to assist in building, gathering resources, and defending against threats.",
      "",
      "**Important Notes:**",
      "",
      "    **Stay Together:** Work as a team to ensure safety and efficiency.",
      "    Keep a Watch: Assign lookout duties to monitor for any potential threats or approaching dangers.",
      "    Log Activities: Keep a detailed log of your activities and findings to assist with future tasks and missions.",
      "",
      "**Survival Tips:**",
      "",
      "    **Use the Environment:** Utilize natural features of the island for shelter, camouflage, and defense.",
      "    Conserve Resources: Use supplies sparingly and plan for long-term survival.",
      "    **Stay Alert:** Be aware of the changing environment and adapt to new challenges as they arise."
    ],
    "groups": {
      "Survival 101": {
        "position": [
          -861,
          -643
        ]
      }
    },
    "icon": {
      "item": {
        "id": "minecraft:campfire",
        "count": 1
      },
      "type": "heracles:item"
    },
    "icon_background": "heracles:textures/gui/quest_backgrounds/default.png",
    "title": {
      "translate": "Immediate Survival"
    }
  },
  "settings": {
    "showDependencyArrow": true,
    "repeatable": false,
    "autoClaimRewards": false,
    "individual_progress": false,
    "hidden": "LOCKED",
    "unlockNotification": false
  }
}